tinysasl/__init__.py
tinysasl-0.1.1.dist-info/LICENSE
tinysasl-0.1.1.dist-info/METADATA
tinysasl-0.1.1.dist-info/WHEEL
tinysasl-0.1.1.dist-info/top_level.txt
tinysasl-0.1.1.dist-info/RECORD
