Metadata-Version: 2.1
Name: tinysasl
Version: 0.1.1
Summary: Tiny SASL-library for Python 3 for SCRAM authentication
Home-page: UNKNOWN
Author: Stan Janssen
Author-email: UNKNOWN
License: UNKNOWN
Platform: UNKNOWN
